smithplot/__init__.py
smithplot/smithaxes.py
smithplot/smithhelper.py
pysmithplot_3.10-0.2.0.dist-info/METADATA
pysmithplot_3.10-0.2.0.dist-info/WHEEL
pysmithplot_3.10-0.2.0.dist-info/top_level.txt
pysmithplot_3.10-0.2.0.dist-info/RECORD
