Metadata-Version: 2.1
Name: pysmithplot-3.10
Version: 0.2.0
Summary: An extension for Matplotlib providing a projection class to generate high quality Smith Chart plots.
Home-page: https://github.com/miesli/pySmithPlot
Author: Mario Krattenmacher
Author-email: Mario.Krattenmacher@semimod.de
License: BSD
Platform: UNKNOWN
Requires-Dist: matplotlib (>=1.2.0)
Requires-Dist: numpy
Requires-Dist: scipy
